LICENSE.txt
MANIFEST.in
README.rst
setup.py
self_balancing_binary_search_tree/__init__.py
self_balancing_binary_search_tree.egg-info/PKG-INFO
self_balancing_binary_search_tree.egg-info/SOURCES.txt
self_balancing_binary_search_tree.egg-info/dependency_links.txt
self_balancing_binary_search_tree.egg-info/top_level.txt