Metadata-Version: 2.1
Name: self-balancing-binary-search-tree
Version: 0.1.4
Summary: A Python implementation of a self balancing binary search tree (AVL Tree). Useful to practice, study and see how a SBBST works.
Home-page: https://github.com/Ualabi/self_balancing_binary_search_tree
Author: Joseandres Hinojoza
Author-email: jhinojoza@outlook.com
License: MIT
Keywords: Self Balancing Binary Search Tree,AVL Tree,Binary Tree,Binary Search Tree,BST,BBST,SBBST
Platform: UNKNOWN
Classifier: Development Status :: 5 - Production/Stable
Classifier: Intended Audience :: Developers
Classifier: Intended Audience :: Education
Classifier: Operating System :: Unix
Classifier: Operating System :: MacOS
Classifier: Operating System :: Microsoft :: Windows
Classifier: License :: OSI Approved :: MIT License
Classifier: Programming Language :: Python
Classifier: Programming Language :: Python :: 2
Classifier: Programming Language :: Python :: 3
Classifier: Topic :: Education
